<?xml version="1.0" encoding="UTF-8"?>

<!-- generated on 2025-07-28 00:15:20 by Eclipse SUMO sumo Version 1.23.1
<sumoConfiguration xmlns:xsi="http://www.w3.org/2001/XMLSchema-instance" xsi:noNamespaceSchemaLocation="http://sumo.dlr.de/xsd/sumoConfiguration.xsd">

    <input>
        <net-file value="SUMO_networks/P1/junction.net.xml"/>
        <route-files value="SUMO_networks/P1/junction.rou.xml"/>
        <additional-files value="SUMO_networks/P1/junction.add.xml"/>
    </input>

    <time>
        <step-length value="0.05"/>
    </time>

    <processing>
        <lateral-resolution value="0.1"/>
    </processing>

    <report>
        <no-warnings value="true"/>
        <no-step-log value="true"/>
    </report>

    <traci_server>
        <remote-port value="57620"/>
    </traci_server>

    <gui_only>
        <start value="true"/>
        <delay value="0"/>
    </gui_only>

</sumoConfiguration>
-->

<detector xmlns:xsi="http://www.w3.org/2001/XMLSchema-instance" xsi:noNamespaceSchemaLocation="http://sumo.dlr.de/xsd/det_e2_file.xsd">
   <interval begin="0.00" end="300.00" id="q1" sampledSeconds="766.57" nVehEntered="29" nVehLeft="24" nVehSeen="29" meanSpeed="2.87" meanTimeLoss="20.70" meanOccupancy="12.65" maxOccupancy="35.00" meanMaxJamLengthInVehicles="1.31" meanMaxJamLengthInMeters="8.09" maxJamLengthInVehicles="6" maxJamLengthInMeters="43.32" jamLengthInVehiclesSum="7884" jamLengthInMetersSum="48513.43" meanHaltingDuration="8.67" maxHaltingDuration="83.20" haltingDurationSum="424.65" meanIntervalHaltingDuration="8.67" maxIntervalHaltingDuration="83.20" intervalHaltingDurationSum="424.65" startedHalts="52.00" meanVehicleNumber="2.56" maxVehicleNumber="7" />
   <interval begin="300.00" end="600.00" id="q1" sampledSeconds="570.86" nVehEntered="23" nVehLeft="25" nVehSeen="28" meanSpeed="3.56" meanTimeLoss="14.99" meanOccupancy="9.37" maxOccupancy="30.00" meanMaxJamLengthInVehicles="0.85" meanMaxJamLengthInMeters="4.96" maxJamLengthInVehicles="5" maxJamLengthInMeters="35.75" jamLengthInVehiclesSum="5073" jamLengthInMetersSum="29746.96" meanHaltingDuration="8.09" maxHaltingDuration="40.20" haltingDurationSum="347.95" meanIntervalHaltingDuration="6.57" maxIntervalHaltingDuration="40.20" intervalHaltingDurationSum="282.35" startedHalts="40.00" meanVehicleNumber="1.90" maxVehicleNumber="6" />
   <interval begin="600.00" end="900.00" id="q1" sampledSeconds="706.07" nVehEntered="28" nVehLeft="28" nVehSeen="31" meanSpeed="2.66" meanTimeLoss="18.28" meanOccupancy="11.66" maxOccupancy="30.00" meanMaxJamLengthInVehicles="1.35" meanMaxJamLengthInMeters="8.23" maxJamLengthInVehicles="5" maxJamLengthInMeters="35.73" jamLengthInVehiclesSum="8083" jamLengthInMetersSum="49394.83" meanHaltingDuration="11.32" maxHaltingDuration="93.20" haltingDurationSum="498.00" meanIntervalHaltingDuration="9.86" maxIntervalHaltingDuration="93.20" intervalHaltingDurationSum="433.75" startedHalts="42.00" meanVehicleNumber="2.35" maxVehicleNumber="6" />
   <interval begin="900.00" end="1200.00" id="q1" sampledSeconds="592.38" nVehEntered="26" nVehLeft="28" nVehSeen="29" meanSpeed="2.98" meanTimeLoss="16.06" meanOccupancy="9.74" maxOccupancy="34.74" meanMaxJamLengthInVehicles="1.03" meanMaxJamLengthInMeters="6.38" maxJamLengthInVehicles="4" maxJamLengthInMeters="28.11" jamLengthInVehiclesSum="6178" jamLengthInMetersSum="38274.46" meanHaltingDuration="8.91" maxHaltingDuration="62.55" haltingDurationSum="356.55" meanIntervalHaltingDuration="8.39" maxIntervalHaltingDuration="62.55" intervalHaltingDurationSum="335.55" startedHalts="38.00" meanVehicleNumber="1.98" maxVehicleNumber="7" />
   <interval begin="1200.00" end="1500.00" id="q1" sampledSeconds="663.21" nVehEntered="29" nVehLeft="29" nVehSeen="30" meanSpeed="3.23" meanTimeLoss="16.95" meanOccupancy="10.91" maxOccupancy="30.00" meanMaxJamLengthInVehicles="1.09" meanMaxJamLengthInMeters="6.70" maxJamLengthInVehicles="4" maxJamLengthInMeters="28.15" jamLengthInVehiclesSum="6567" jamLengthInMetersSum="40173.53" meanHaltingDuration="8.00" maxHaltingDuration="70.15" haltingDurationSum="360.05" meanIntervalHaltingDuration="8.00" maxIntervalHaltingDuration="70.15" intervalHaltingDurationSum="360.05" startedHalts="45.00" meanVehicleNumber="2.21" maxVehicleNumber="6" />
   <interval begin="1500.00" end="1800.00" id="q1" sampledSeconds="554.66" nVehEntered="27" nVehLeft="26" nVehSeen="28" meanSpeed="3.80" meanTimeLoss="14.40" meanOccupancy="9.13" maxOccupancy="25.00" meanMaxJamLengthInVehicles="0.82" meanMaxJamLengthInMeters="4.78" maxJamLengthInVehicles="3" maxJamLengthInMeters="20.65" jamLengthInVehiclesSum="4907" jamLengthInMetersSum="28694.32" meanHaltingDuration="6.98" maxHaltingDuration="46.65" haltingDurationSum="272.35" meanIntervalHaltingDuration="6.97" maxIntervalHaltingDuration="46.65" intervalHaltingDurationSum="271.95" startedHalts="38.00" meanVehicleNumber="1.85" maxVehicleNumber="5" />
   <interval begin="1800.00" end="2100.00" id="q1" sampledSeconds="557.56" nVehEntered="26" nVehLeft="24" nVehSeen="28" meanSpeed="3.46" meanTimeLoss="14.85" meanOccupancy="9.17" maxOccupancy="27.00" meanMaxJamLengthInVehicles="0.83" meanMaxJamLengthInMeters="4.96" maxJamLengthInVehicles="4" maxJamLengthInMeters="28.26" jamLengthInVehiclesSum="4996" jamLengthInMetersSum="29761.40" meanHaltingDuration="6.81" maxHaltingDuration="54.20" haltingDurationSum="286.05" meanIntervalHaltingDuration="6.54" maxIntervalHaltingDuration="54.20" intervalHaltingDurationSum="274.75" startedHalts="43.00" meanVehicleNumber="1.86" maxVehicleNumber="6" />
   <interval begin="2100.00" end="2400.00" id="q1" sampledSeconds="995.84" nVehEntered="30" nVehLeft="33" nVehSeen="34" meanSpeed="2.55" meanTimeLoss="23.80" meanOccupancy="16.42" maxOccupancy="40.00" meanMaxJamLengthInVehicles="1.84" meanMaxJamLengthInMeters="12.24" maxJamLengthInVehicles="8" maxJamLengthInMeters="58.15" jamLengthInVehiclesSum="11049" jamLengthInMetersSum="73451.92" meanHaltingDuration="11.30" maxHaltingDuration="66.75" haltingDurationSum="655.30" meanIntervalHaltingDuration="10.18" maxIntervalHaltingDuration="63.65" intervalHaltingDurationSum="590.60" startedHalts="57.00" meanVehicleNumber="3.32" maxVehicleNumber="8" />
   <interval begin="2400.00" end="2700.00" id="q1" sampledSeconds="536.29" nVehEntered="24" nVehLeft="23" nVehSeen="25" meanSpeed="3.57" meanTimeLoss="15.69" meanOccupancy="8.83" maxOccupancy="30.00" meanMaxJamLengthInVehicles="0.82" meanMaxJamLengthInMeters="4.75" maxJamLengthInVehicles="4" maxJamLengthInMeters="28.38" jamLengthInVehiclesSum="4912" jamLengthInMetersSum="28493.28" meanHaltingDuration="7.02" maxHaltingDuration="35.55" haltingDurationSum="273.85" meanIntervalHaltingDuration="7.02" maxIntervalHaltingDuration="35.55" intervalHaltingDurationSum="273.85" startedHalts="39.00" meanVehicleNumber="1.79" maxVehicleNumber="6" />
   <interval begin="2700.00" end="3000.00" id="q1" sampledSeconds="570.50" nVehEntered="26" nVehLeft="25" nVehSeen="28" meanSpeed="3.66" meanTimeLoss="14.94" meanOccupancy="9.38" maxOccupancy="25.00" meanMaxJamLengthInVehicles="0.85" meanMaxJamLengthInMeters="4.75" maxJamLengthInVehicles="4" maxJamLengthInMeters="28.09" jamLengthInVehiclesSum="5095" jamLengthInMetersSum="28529.32" meanHaltingDuration="7.66" maxHaltingDuration="64.40" haltingDurationSum="306.20" meanIntervalHaltingDuration="7.03" maxIntervalHaltingDuration="64.40" intervalHaltingDurationSum="281.20" startedHalts="39.00" meanVehicleNumber="1.90" maxVehicleNumber="5" />
   <interval begin="3000.00" end="3300.00" id="q1" sampledSeconds="490.44" nVehEntered="20" nVehLeft="22" nVehSeen="23" meanSpeed="3.57" meanTimeLoss="15.94" meanOccupancy="8.04" maxOccupancy="20.00" meanMaxJamLengthInVehicles="0.76" meanMaxJamLengthInMeters="4.68" maxJamLengthInVehicles="3" maxJamLengthInMeters="20.67" jamLengthInVehiclesSum="4589" jamLengthInMetersSum="28070.70" meanHaltingDuration="8.78" maxHaltingDuration="39.65" haltingDurationSum="289.75" meanIntervalHaltingDuration="7.66" maxIntervalHaltingDuration="38.00" intervalHaltingDurationSum="252.65" startedHalts="32.00" meanVehicleNumber="1.64" maxVehicleNumber="4" />
   <interval begin="3300.00" end="3600.00" id="q1" sampledSeconds="857.92" nVehEntered="21" nVehLeft="22" nVehSeen="22" meanSpeed="1.96" meanTimeLoss="33.35" meanOccupancy="14.19" maxOccupancy="35.00" meanMaxJamLengthInVehicles="1.92" meanMaxJamLengthInMeters="12.43" maxJamLengthInVehicles="6" maxJamLengthInMeters="43.20" jamLengthInVehiclesSum="11530" jamLengthInMetersSum="74582.67" meanHaltingDuration="16.32" maxHaltingDuration="79.05" haltingDurationSum="604.05" meanIntervalHaltingDuration="16.32" maxIntervalHaltingDuration="79.05" intervalHaltingDurationSum="604.05" startedHalts="38.00" meanVehicleNumber="2.86" maxVehicleNumber="7" />
   <interval begin="3600.00" end="3648.00" id="q1" sampledSeconds="0.00" nVehEntered="0" nVehLeft="0" nVehSeen="0" meanSpeed="-1.00" meanTimeLoss="-1.00" meanOccupancy="0.00" maxOccupancy="0.00" meanMaxJamLengthInVehicles="0.00" meanMaxJamLengthInMeters="0.00" maxJamLengthInVehicles="0" maxJamLengthInMeters="0.00" jamLengthInVehiclesSum="0" jamLengthInMetersSum="0.00" meanHaltingDuration="0.00" maxHaltingDuration="0.00" haltingDurationSum="0.00" meanIntervalHaltingDuration="0.00" maxIntervalHaltingDuration="0.00" intervalHaltingDurationSum="0.00" startedHalts="0.00" meanVehicleNumber="0.00" maxVehicleNumber="0" />
</detector>
